README.rst
setup.py
fuzzy_fabric/__init__.py
fuzzy_fabric/fabfile.py
fuzzy_fabric/main.py
fuzzy_fabric/old_path.py
fuzzy_fabric/old_utils.py
fuzzy_fabric/templates
fuzzy_fabric/utils.py
fuzzy_fabric.egg-info/PKG-INFO
fuzzy_fabric.egg-info/SOURCES.txt
fuzzy_fabric.egg-info/dependency_links.txt
fuzzy_fabric.egg-info/entry_points.txt
fuzzy_fabric.egg-info/requires.txt
fuzzy_fabric.egg-info/top_level.txt
fuzzy_fabric/templates/
fuzzy_fabric/templates/.gitignore
fuzzy_fabric/templates/.hgignore
fuzzy_fabric/templates/README.rst
fuzzy_fabric/templates/fabric.ini
fuzzy_fabric/templates/module.py
fuzzy_fabric/templates/nginx
fuzzy_fabric/templates/setup.py
fuzzy_fabric/templates/nginx/
fuzzy_fabric/templates/nginx/nginx.conf
fuzzy_fabric/templates/nginx/site.conf