Metadata-Version: 1.1
Name: fuzzy-fabric
Version: 0.6.3
Summary: Fuzzy Functions For Fabric
Home-page: https://github.com/dimka665/fuzzy-fabric
Author: Dmitry Voronin
Author-email: dimka665@gmail.com
License: MIT License
Keywords: fuzzy functions for fabric
Platform: UNKNOWN
Classifier: License :: OSI Approved :: MIT License
Classifier: Programming Language :: Python
Classifier: Programming Language :: Python :: 2.7
Classifier: Programming Language :: Python :: 3
Classifier: Programming Language :: Python :: 3.3
Classifier: Programming Language :: Python :: 3.4
